Workbook

Sheet Sheet1
A1: 日期_月 | B1: 核代账户id | C1: 核代账户名称 | D1: 广告包名 | E1: 地域 | F1: DSP收入 | G1: 包名区域匹配 | H1: 数鲸归属 | I1: 争议归属 | J1: 备注
A2: 202512 | B2: 368 | C2: Avow GmbH | D2: com.finaccel.android | E2: SA | F2: 54785.83 | G2: =VLOOKUP(D2,'【For 计提】包名对应区域'!A:B,2,0) -> SEA
A3: 202512 | B3: 368 | C3: Avow GmbH | D3: com.wetter.androidclient | E3: WEU/CEE | F3: 36759.96 | G3: =VLOOKUP(D3,'【For 计提】包名对应区域'!A:B,2,0) -> WEU/CEE
A4: 202512 | B4: 368 | C4: Avow GmbH | D4: net.peakgames.Yuzbir | F4: 26876.64 | G4: =VLOOKUP(D4,'【For 计提】包名对应区域'!A:B,2,0) -> NA
A5: 202512 | B5: 8342 | C5: Flymobi Technology Group Limited | D5: com.voicemaker.android | E5: APAC | F5: 26809.7 | G5: =VLOOKUP(D5,'【For 计提】包名对应区域'!A:B,2,0) -> APAC
A6: 202512 | B6: 8342 | C6: Flymobi Technology Group Limited | D6: com.live.soulchill | E6: SEA | F6: 19707.52 | G6: =VLOOKUP(D6,'【For 计提】包名对应区域'!A:B,2,0) -> APAC
A7: 202512 | B7: 368 | C7: Avow GmbH | D7: com.revolut.revolut | F7: 18718.77 | G7: =VLOOKUP(D7,'【For 计提】包名对应区域'!A:B,2,0) -> WEU/CEE
A8: 202512 | B8: 8342 | C8: Flymobi Technology Group Limited | D8: com.hotplay.bricksballs | E8: APAC | F8: 14162.48 | G8: =VLOOKUP(D8,'【For 计提】包名对应区域'!A:B,2,0) -> APAC
A9: 202512 | B9: 368 | C9: Avow GmbH | D9: com.mercadopago.wallet | F9: 13064 | G9: =VLOOKUP(D9,'【For 计提】包名对应区域'!A:B,2,0) -> LATAM
A10: 202512 | B10: 8342 | C10: Flymobi Technology Group Limited | D10: com.xparty.androidapp | E10: APAC | F10: 13012.18 | G10: =VLOOKUP(D10,'【For 计提】包名对应区域'!A:B,2,0) -> APAC
A11: 202512 | B11: 8342 | C11: Flymobi Technology Group Limited | D11: com.voicechat.live.group | E11: APAC | F11: 12969.65 | G11: =VLOOKUP(D11,'【For 计提】包名对应区域'!A:B,2,0) -> APAC
A12: 202512 | B12: 368 | C12: Avow GmbH | F12: 12305.9 | G12: WEU
A13: 202512 | B13: 8342 | C13: Flymobi Technology Group Limited | D13: com.hotplay.babyexcavator | E13: APAC | F13: 11167.48 | G13: =VLOOKUP(D13,'【For 计提】包名对应区域'!A:B,2,0) -> APAC
A14: 202512 | B14: 368 | C14: Avow GmbH | D14: com.tripledot.solitaire | E14: WEU/CEE | F14: 10350.23 | G14: =VLOOKUP(D14,'【For 计提】包名对应区域'!A:B,2,0) -> WEU/CEE
A15: 202512 | B15: 8342 | C15: Flymobi Technology Group Limited | D15: com.wallpaperx.main | F15: 9657.22 | G15: =VLOOKUP(D15,'【For 计提】包名对应区域'!A:B,2,0) -> APAC
A16: 202512 | B16: 8342 | C16: Flymobi Technology Group Limited | D16: com.hotplay.petexplosion | E16: APAC | F16: 9043.54 | G16: =VLOOKUP(D16,'【For 计提】包名对应区域'!A:B,2,0) -> APAC
A17: 202512 | B17: 368 | C17: Avow GmbH | D17: com.axlebolt.standoff2 | E17: MENA | F17: 9032.5 | G17: =VLOOKUP(D17,'【For 计提】包名对应区域'!A:B,2,0) -> CIS
A18: 202512 | B18: 368 | C18: Avow GmbH | D18: com.akbank.android.apps.akbank_direkt | E18: MENA | F18: 8404.81 | G18: =VLOOKUP(D18,'【For 计提】包名对应区域'!A:B,2,0) -> MENA
A19: 202512 | B19: 8342 | C19: Flymobi Technology Group Limited | D19: com.fusionmind.crazydrive | E19: APAC | F19: 7922.91 | G19: =VLOOKUP(D19,'【For 计提】包名对应区域'!A:B,2,0) -> APAC
A20: 202512 | B20: 8342 | C20: Flymobi Technology Group Limited | D20: com.xenalite.androidapp | E20: APAC | F20: 7831.51 | G20: =VLOOKUP(D20,'【For 计提】包名对应区域'!A:B,2,0) -> APAC
A21: 202512 | B21: 8342 | C21: Flymobi Technology Group Limited | D21: com.aultkm.calandexlock | E21: APAC | F21: 7811.68 | G21: =VLOOKUP(D21,'【For 计提】包名对应区域'!A:B,2,0) -> APAC
A22: 202512 | B22: 8342 | C22: Flymobi Technology Group Limited | D22: com.biotalem.deskclock | E22: APAC | F22: 7773.26 | G22: =VLOOKUP(D22,'【For 计提】包名对应区域'!A:B,2,0) -> APAC
A23: 202512 | B23: 8342 | C23: Flymobi Technology Group Limited | D23: com.fruitdrop.combine | E23: WEU/CEE | F23: 7658.54 | G23: =VLOOKUP(D23,'【For 计提】包名对应区域'!A:B,2,0) -> WEU/CEE
A24: 202512 | B24: 8342 | C24: Flymobi Technology Group Limited | D24: com.zombiedefense.battle | E24: WEU/CEE | F24: 7614.91 | G24: =VLOOKUP(D24,'【For 计提】包名对应区域'!A:B,2,0) -> APAC
A25: 202512 | B25: 368 | C25: Avow GmbH | D25: com.zm.watersort | E25: WEU/CEE | F25: 7323.79 | G25: =VLOOKUP(D25,'【For 计提】包名对应区域'!A:B,2,0) -> WEU/CEE
A26: 202512 | B26: 8342 | C26: Flymobi Technology Group Limited | D26: com.gridlock.vault | E26: WEU/CEE | F26: 7187.14 | G26: =VLOOKUP(D26,'【For 计提】包名对应区域'!A:B,2,0) -> APAC
A27: 202512 | B27: 8342 | C27: Flymobi Technology Group Limited | D27: com.fintopia.mxcredmex | E27: LATAM | F27: 6766.43 | G27: =VLOOKUP(D27,'【For 计提】包名对应区域'!A:B,2,0) -> LATAM
... A30: 202512 | B30: 368 | C30: Avow GmbH | D30: com.transferwise.android | E30: WEU/CEE | F30: 6172.01 | G30: =VLOOKUP(D30,'【For 计提】包名对应区域'!A:B,2,0) -> WEU/CEE
A31: 202512 | B31: 368 | C31: Avow GmbH | D31: com.luizalabs.mlapp | F31: 5598.02 | G31: =VLOOKUP(D31,'【For 计提】包名对应区域'!A:B,2,0) -> LATAM
A32: 202512 | B32: 368 | C32: Avow GmbH | D32: com.mobirix.swipebrick2 | F32: 5492.04 | G32: =VLOOKUP(D32,'【For 计提】包名对应区域'!A:B,2,0) -> APAC
A33: 202512 | B33: 368 | C33: Avow GmbH | D33: com.callapp.contacts | E33: SEA | F33: 5440.12 | G33: =VLOOKUP(D33,'【For 计提】包名对应区域'!A:B,2,0) -> MENA
A34: 202512 | B34: 368 | C34: Avow GmbH | D34: com.ticno.olymptrade | E34: SEA | F34: 5363.71 | G34: =VLOOKUP(D34,'【For 计提】包名对应区域'!A:B,2,0) -> SEA
A35: 202512 | B35: 8342 | C35: Flymobi Technology Group Limited | D35: com.hotplay.puzzlegames | E35: APAC | F35: 5260.84 | G35: =VLOOKUP(D35,'【For 计提】包名对应区域'!A:B,2,0) -> APAC
A36: 202512 | B36: 368 | C36: Avow GmbH | D36: com.wolt.android | F36: 5219.62 | G36: =VLOOKUP(D36,'【For 计提】包名对应区域'!A:B,2,0) -> WEU/CEE
A37: 202512 | B37: 368 | C37: Avow GmbH | D37: com.huuuge.casino.slots | F37: 5022.28 | G37: =VLOOKUP(D37,'【For 计提】包名对应区域'!A:B,2,0) -> WEU/CEE
A38: 202512 | B38: 8342 | C38: Flymobi Technology Group Limited | D38: com.fpg.thiefstickman | E38: APAC | F38: 4983.4 | G38: =VLOOKUP(D38,'【For 计提】包名对应区域'!A:B,2,0) -> APAC
A39: 202512 | B39: 8342 | C39: Flymobi Technology Group Limited | D39: com.fpg.snakeclash | E39: APAC | F39: 4914.78 | G39: =VLOOKUP(D39,'【For 计提】包名对应区域'!A:B,2,0) -> APAC
A40: 202512 | B40: 368 | C40: Avow GmbH | D40: com.muba.anuncios | F40: 4846.27 | G40: =VLOOKUP(D40,'【For 计提】包名对应区域'!A:B,2,0) -> WEU/CEE
A41: 202512 | B41: 8342 | C41: Flymobi Technology Group Limited | D41: com.immomo.biz.yaahlan | E41: APAC | F41: 4553.84 | G41: =VLOOKUP(D41,'【For 计提】包名对应区域'!A:B,2,0) -> APAC
A42: 202512 | B42: 8342 | C42: Flymobi Technology Group Limited | D42: com.chatchill.app | F42: 4479.25 | G42: =VLOOKUP(D42,'【For 计提】包名对应区域'!A:B,2,0) -> APAC
A43: 202512 | B43: 8342 | C43: Flymobi Technology Group Limited | D43: com.yg.sf.minigames | E43: APAC | F43: 4426.07 | G43: =VLOOKUP(D43,'【For 计提】包名对应区域'!A:B,2,0) -> APAC
A44: 202512 | B44: 368 | C44: Avow GmbH | D44: com.mercadolibre | E44: LATAM | F44: 4397.77 | G44: =VLOOKUP(D44,'【For 计提】包名对应区域'!A:B,2,0) -> LATAM
A45: 202512 | B45: 8342 | C45: Flymobi Technology Group Limited | D45: com.fusionmind.tocalifeworld | E45: APAC | F45: 4376.72 | G45: =VLOOKUP(D45,'【For 计提】包名对应区域'!A:B,2,0) -> APAC
A46: 202512 | B46: 368 | C46: Avow GmbH | D46: com.finex.trading | E46: SEA | F46: 4351.22 | G46: =VLOOKUP(D46,'【For 计提】包名对应区域'!A:B,2,0) -> SEA
A47: 202512 | B47: 368 | C47: Avow GmbH | D47: net.wooga.junes_journey_hidden_object_mystery_game | F47: 4281.41 | G47: =VLOOKUP(D47,'【For 计提】包名对应区域'!A:B,2,0) -> WEU/CEE
A48: 202512 | B48: 8342 | C48: Flymobi Technology Group Limited | D48: com.kongnunm.colorjump | E48: APAC | F48: 4231.97 | G48: =VLOOKUP(D48,'【For 计提】包名对应区域'!A:B,2,0) -> APAC
A49: 202512 | B49: 8342 | C49: Flymobi Technology Group Limited | D49: com.hotplay.thebees | E49: APAC | F49: 4195.55 | G49: =VLOOKUP(D49,'【For 计提】包名对应区域'!A:B,2,0) -> APAC
A50: 202512 | B50: 8342 | C50: Flymobi Technology Group Limited | D50: com.gamoremi.catdiary | E50: APAC | F50: 4139.45 | G50: =VLOOKUP(D50,'【For 计提】包名对应区域'!A:B,2,0) -> APAC
A51: 202512 | B51: 8342 | C51: Flymobi Technology Group Limited | D51: com.fpl.car.race | E51: APAC | F51: 4048.63 | G51: =VLOOKUP(D51,'【For 计提】包名对应区域'!A:B,2,0) -> APAC
A52: 202512 | B52: 368 | C52: Avow GmbH | D52: com.openmygame.games.android.wordpizza | E52: MENA | F52: 3811.99 | G52: =VLOOKUP(D52,'【For 计提】包名对应区域'!A:B,2,0) -> CIS
A53: 202512 | B53: 8342 | C53: Flymobi Technology Group Limited | D53: com.fpg.skyballs | E53: APAC | F53: 3759.71 | G53: =VLOOKUP(D53,'【For 计提】包名对应区域'!A:B,2,0) -> APAC
A54: 202512 | B54: 368 | C54: Avow GmbH | D54: com.octainvest | F54: 3694.39 | G54: =IFERROR(VLOOKUP(D54,'【For 计提】包名对应区域'!A:B,2,0),"新增包名待匹配") -> 新增包名待匹配 | H54: =E54 -> 0 | I54: MENA | J54: GP开发者归属在MENA
A55: 202512 | B55: 368 | C55: Avow GmbH | D55: funvent.tilepark | E55: MENA | F55: 3693.91 | G55: =VLOOKUP(D55,'【For 计提】包名对应区域'!A:B,2,0) -> NA
A56: 202512 | B56: 368 | C56: Avow GmbH | D56: com.MadOut.BIG | F56: 3603.11 | G56: =VLOOKUP(D56,'【For 计提】包名对应区域'!A:B,2,0) -> WEU/CEE
A57: 202512 | B57: 368 | C57: Avow GmbH | D57: io.supercent.pizzaidle | F57: 3598.61 | G57: =VLOOKUP(D57,'【For 计提】包名对应区域'!A:B,2,0) -> APAC
A58: 202512 | B58: 8342 | C58: Flymobi Technology Group Limited | D58: com.kkii | E58: APAC | F58: 3284.95 | G58: =VLOOKUP(D58,'【For 计提】包名对应区域'!A:B,2,0) -> APAC
A59: 202512 | B59: 368 | C59: Avow GmbH | D59: games.spearmint.triplecrush | E59: MENA | F59: 3250.12 | G59: =VLOOKUP(D59,'【For 计提】包名对应区域'!A:B,2,0) -> MENA
A60: 202512 | B60: 368 | C60: Avow GmbH | D60: net.btpro.client.karaca | F60: 3232.5 | G60: =VLOOKUP(D60,'【For 计提】包名对应区域'!A:B,2,0) -> MENA
A61: 202512 | B61: 368 | C61: Avow GmbH | D61: com.xm.webapp.connect | F61: 3153.5 | G61: =VLOOKUP(D61,'【For 计提】包名对应区域'!A:B,2,0) -> WEU/CEE
A62: 202512 | B62: 8342 | C62: Flymobi Technology Group Limited | D62: com.yg.extreme.moto | E62: APAC | F62: 3016.85 | G62: =VLOOKUP(D62,'【For 计提】包名对应区域'!A:B,2,0) -> APAC
A63: 202512 | B63: 368 | C63: Avow GmbH | D63: com.vitastudio.mahjong | E63: APAC | F63: 2997.9 | G63: =VLOOKUP(D63,'【For 计提】包名对应区域'!A:B,2,0) -> APAC
A64: 202512 | B64: 368 | C64: Avow GmbH | D64: de.lotto24.app | E64: WEU/CEE | F64: 2936.53 | G64: =VLOOKUP(D64,'【For 计提】包名对应区域'!A:B,2,0) -> WEU/CEE
A65: 202512 | B65: 8342 | C65: Flymobi Technology Group Limited | D65: in.amazon.mShop.android.shopping | E65: SA | F65: 2910.09 | G65: =VLOOKUP(D65,'【For 计提】包名对应区域'!A:B,2,0) -> SA
A66: 202512 | B66: 368 | C66: Avow GmbH | D66: br.com.belezanaweb.android | F66: 2814.75 | G66: =VLOOKUP(D66,'【For 计提】包名对应区域'!A:B,2,0) -> LATAM
A67: 202512 | B67: 8342 | C67: Flymobi Technology Group Limited | D67: com.vilikestech.bubble | E67: APAC | F67: 2695.62 | G67: =VLOOKUP(D67,'【For 计提】包名对应区域'!A:B,2,0) -> APAC
A68: 202512 | B68: 368 | C68: Avow GmbH | D68: de.autodoc.gmbh | E68: SEA | F68: 2689.46 | G68: =VLOOKUP(D68,'【For 计提】包名对应区域'!A:B,2,0) -> WEU/CEE
A69: 202512 | B69: 368 | C69: Avow GmbH | D69: vn.com.vng.zalopay | E69: SEA | F69: 2658.97 | G69: =VLOOKUP(D69,'【For 计提】包名对应区域'!A:B,2,0) -> SEA
A70: 202512 | B70: 368 | C70: Avow GmbH | D70: com.anuntis.fotocasa | F70: 2650.86 | G70: =VLOOKUP(D70,'【For 计提】包名对应区域'!A:B,2,0) -> WEU/CEE
A71: 202512 | B71: 8342 | C71: Flymobi Technology Group Limited | D71: com.fpg.antistress.relaxing | E71: APAC | F71: 2555.47 | G71: =VLOOKUP(D71,'【For 计提】包名对应区域'!A:B,2,0) -> APAC
A72: 202512 | B72: 8342 | C72: Flymobi Technology Group Limited | D72: com.fpl.mobile.phone | E72: APAC | F72: 2475.32 | G72: =VLOOKUP(D72,'【For 计提】包名对应区域'!A:B,2,0) -> APAC
A73: 202512 | B73: 368 | C73: Avow GmbH | D73: com.olympbroker.android | F73: 2432.68 | G73: =VLOOKUP(D73,'【For 计提】包名对应区域'!A:B,2,0) -> LATAM
A74: 202512 | B74: 8342 | C74: Flymobi Technology Group Limited | D74: com.gamxoam.marbles | E74: APAC | F74: 2417.89 | G74: =VLOOKUP(D74,'【For 计提】包名对应区域'!A:B,2,0) -> APAC
A75: 202512 | B75: 368 | C75: Avow GmbH | D75: com.truecaller | E75: SEA | F75: 2303.76 | G75: =VLOOKUP(D75,'【For 计提】包名对应区域'!A:B,2,0) -> WEU/CEE
A76: 202512 | B76: 8342 | C76: Flymobi Technology Group Limited | D76: com.fpl.relaxing.pop | E76: APAC | F76: 2295.9 | G76: =VLOOKUP(D76,'【For 计提】包名对应区域'!A:B,2,0) -> APAC
A77: 202512 | B77: 8342 | C77: Flymobi Technology Group Limited | D77: com.stickrun.mountain | E77: WEU/CEE | F77: 2286.38 | G77: =IFERROR(VLOOKUP(D77,'【For 计提】包名对应区域'!A:B,2,0),"新增包名待匹配") -> 新增包名待匹配 | H77: =E77 -> WEU/CEE
A78: 202512 | B78: 8342 | C78: Flymobi Technology Group Limited | D78: com.beastfuse.evolve | E78: WEU/CEE | F78: 2220.97 | G78: =IFERROR(VLOOKUP(D78,'【For 计提】包名对应区域'!A:B,2,0),"新增包名待匹配") -> 新增包名待匹配 | H78: =E78 -> WEU/CEE
A79: 202512 | B79: 368 | C79: Avow GmbH | D79: com.globo.globotv | F79: 2220.51 | G79: =VLOOKUP(D79,'【For 计提】包名对应区域'!A:B,2,0) -> LATAM
A80: 202512 | B80: 8342 | C80: Flymobi Technology Group Limited | D80: com.tongueswing.runner | E80: WEU/CEE | F80: 2178.94 | G80: =IFERROR(VLOOKUP(D80,'【For 计提】包名对应区域'!A:B,2,0),"新增包名待匹配") -> 新增包名待匹配 | H80: =E80 -> WEU/CEE
A81: 202512 | B81: 368 | C81: Avow GmbH | D81: br.com.ifood.driver.app | F81: 2161.08 | G81: =VLOOKUP(D81,'【For 计提】包名对应区域'!A:B,2,0) -> LATAM
A82: 202512 | B82: 368 | C82: Avow GmbH | D82: br.com.brainweb.ifood | F82: 2139.08 | G82: =VLOOKUP(D82,'【For 计提】包名对应区域'!A:B,2,0) -> LATAM
A83: 202512 | B83: 368 | C83: Avow GmbH | D83: com.betway.casino | E83: SEA | F83: 2138.33 | G83: =VLOOKUP(D83,'【For 计提】包名对应区域'!A:B,2,0) -> SEA
A84: 202512 | B84: 368 | C84: Avow GmbH | D84: com.paymaya.negosyo | F84: 2069.1 | G84: =VLOOKUP(D84,'【For 计提】包名对应区域'!A:B,2,0) -> SEA
A85: 202512 | B85: 8342 | C85: Flymobi Technology Group Limited | D85: com.boxpierce.oneshot | E85: WEU/CEE | F85: 2066.09 | G85: =IFERROR(VLOOKUP(D85,'【For 计提】包名对应区域'!A:B,2,0),"新增包名待匹配") -> 新增包名待匹配 | H85: =E85 -> WEU/CEE
A86: 202512 | B86: 368 | C86: Avow GmbH | D86: coches.net | E86: WEU/CEE | F86: 2028.62 | G86: =VLOOKUP(D86,'【For 计提】包名对应区域'!A:B,2,0) -> LATAM
A87: 202512 | B87: 368 | C87: Avow GmbH | D87: br.com.neon | F87: 2012.56 | G87: =VLOOKUP(D87,'【For 计提】包名对应区域'!A:B,2,0) -> LATAM
A88: 202512 | B88: 8342 | C88: Flymobi Technology Group Limited | D88: com.fusionmind.redball4 | E88: APAC | F88: 2005.22 | G88: =VLOOKUP(D88,'【For 计提】包名对应区域'!A:B,2,0) -> APAC
A89: 202512 | B89: 368 | C89: Avow GmbH | D89: co.bitx.android.wallet | F89: 1866 | G89: =VLOOKUP(D89,'【For 计提】包名对应区域'!A:B,2,0) -> WEU/CEE
A90: 202512 | B90: 8342 | C90: Flymobi Technology Group Limited | D90: com.wifimmi.radar | E90: APAC | F90: 1865.99 | G90: =VLOOKUP(D90,'【For 计提】包名对应区域'!A:B,2,0) -> APAC
A91: 202512 | B91: 368 | C91: Avow GmbH | D91: com.sgiggle.production | F91: 1836.02 | G91: =VLOOKUP(D91,'【For 计提】包名对应区域'!A:B,2,0) -> NA
A92: 202512 | B92: 368 | C92: Avow GmbH | D92: com.weegoon.thiefpuzzle | E92: SEA | F92: 1829.02 | G92: =VLOOKUP(D92,'【For 计提】包名对应区域'!A:B,2,0) -> WEU/CEE
A93: 202512 | B93: 368 | C93: Avow GmbH | D93: com.gameduell.romme.treff.kartenspiel | F93: 1792.42 | G93: =VLOOKUP(D93,'【For 计提】包名对应区域'!A:B,2,0) -> WEU/CEE
A94: 202512 | B94: 368 | C94: Avow GmbH | D94: com.xm.webapp.global | F94: 1632.06 | G94: =VLOOKUP(D94,'【For 计提】包名对应区域'!A:B,2,0) -> MENA
A95: 202512 | B95: 368 | C95: Avow GmbH | D95: org.fxclub.libertex | F95: 1619.24 | G95: =VLOOKUP(D95,'【For 计提】包名对应区域'!A:B,2,0) -> WEU/CEE
A96: 202512 | B96: 368 | C96: Avow GmbH | D96: com.xm.webapp | E96: APAC | F96: 1598.73 | G96: =VLOOKUP(D96,'【For 计提】包名对应区域'!A:B,2,0) -> APAC
A97: 202512 | B97: 368 | C97: Avow GmbH | D97: com.movile.playkids.pkxd | F97: 1512.58 | G97: =VLOOKUP(D97,'【For 计提】包名对应区域'!A:B,2,0) -> LATAM
A98: 202512 | B98: 8342 | C98: Flymobi Technology Group Limited | D98: com.anhengsm.bloom | E98: APAC | F98: 1412.41 | G98: =VLOOKUP(D98,'【For 计提】包名对应区域'!A:B,2,0) -> APAC
A99: 202512 | B99: 368 | C99: Avow GmbH | D99: com.nomadfintech.bank.app.android | F99: 1402.06 | G99: =VLOOKUP(D99,'【For 计提】包名对应区域'!A:B,2,0) -> LATAM
A100: 202512 | B100: 8342 | C100: Flymobi Technology Group Limited | D100: com.vilykkeme.compass | E100: APAC | F100: 1325.16 | G100: =VLOOKUP(D100,'【For 计提】包名对应区域'!A:B,2,0) -> APAC
A101: 202512 | B101: 368 | C101: Avow GmbH | D101: th.co.supersports | F101: 1248.51 | G101: =VLOOKUP(D101,'【For 计提】包名对应区域'!A:B,2,0) -> SEA
A102: 202512 | B102: 368 | C102: Avow GmbH | D102: com.mdf.repsol | F102: 1083.06 | G102: =VLOOKUP(D102,'【For 计提】包名对应区域'!A:B,2,0) -> WEU/CEE
...

Sheet 【For 计提】包名对应区域
A1: 客户下包名 | B1: 包名所属区域 | C1: 是否重复
A2: zps.game.pusoy.th | B2: SEA | C2: =COUNTIF(A:A,A2) -> 1
A3: zoom.magnifier.clarity.durable.assist | B3: WEU/CEE | C3: =COUNTIF(A:A,A3) -> 1
A4: zentro.warp.zw | B4: APAC | C4: =COUNTIF(A:A,A4) -> 1
A5: zen.task.zt | B5: APAC | C5: =COUNTIF(A:A,A5) -> 1
A6: zebpay.Application | B6: SA | C6: =COUNTIF(A:A,A6) -> 1
A7: zahleb.me | B7: CIS | C7: =COUNTIF(A:A,A7) -> 1
A8: za.co.travelstart.flapp | B8: APAC | C8: =COUNTIF(A:A,A8) -> 1
A9: yyhg.as.mi | B9: APAC | C9: =COUNTIF(A:A,A9) -> 1
A10: yyhg.ar3.mi | B10: APAC | C10: =COUNTIF(A:A,A10) -> 1
A11: youdrive.today | B11: CIS | C11: =COUNTIF(A:A,A11) -> 1
A12: yay.marvelous.orange.corp | B12: CIS | C12: =COUNTIF(A:A,A12) -> 1
A13: y6uzdaz1.web | B13: APAC | C13: =COUNTIF(A:A,A13) -> 1
... A5580: sg.com.cyclecarriage.mycnc | B5580: SEA | C5580: =COUNTIF(A:A,A5580) -> 1
